setup.py
Factorlib.egg-info/PKG-INFO
Factorlib.egg-info/SOURCES.txt
Factorlib.egg-info/dependency_links.txt
Factorlib.egg-info/top_level.txt
factorlib.egg-info/PKG-INFO
factorlib.egg-info/SOURCES.txt
factorlib.egg-info/dependency_links.txt
factorlib.egg-info/top_level.txt
utils/__init__.py
utils/helpers.py
utils/system.py
utils/datetime_maps/__init__.py